mafw/__about__.py
mafw/__init__.py
mafw/active.py
mafw/decorators.py
mafw/enumerators.py
mafw/hookspecs.py
mafw/mafw_errors.py
mafw/plugin_manager.py
mafw/plugins.py
mafw/processor.py
mafw/runner.py
mafw/timer.py
mafw/db/__init__.py
mafw/db/db_configurations.py
mafw/db/db_filter.py
mafw/db/db_model.py
mafw/db/db_types.py
mafw/db/db_wizard.py
mafw/db/fields.py
mafw/db/std_tables.py
mafw/db/trigger.py
mafw/examples/__init__.py
mafw/examples/db_processors.py
mafw/examples/importer_example.py
mafw/examples/loop_modifier.py
mafw/examples/multi_primary.py
mafw/examples/processor_list.py
mafw/examples/sum_processor.py
mafw/processor_library/__init__.py
mafw/processor_library/abstract_plotter.py
mafw/processor_library/importer.py
mafw/processor_library/sns_plotter.py
mafw/scripts/__init__.py
mafw/scripts/mafw_exe.py
mafw/scripts/update_changelog.py
mafw/scripts/update_notice.py
mafw/tools/__init__.py
mafw/tools/db_tools.py
mafw/tools/file_tools.py
mafw/tools/pandas_tools.py
mafw/tools/regexp.py
mafw/tools/toml_tools.py
mafw/ui/__init__.py
mafw/ui/abstract_user_interface.py
mafw/ui/console_user_interface.py
mafw/ui/rich_user_interface.py
mafw-1.4.0.dist-info/METADATA
mafw-1.4.0.dist-info/WHEEL
mafw-1.4.0.dist-info/entry_points.txt
mafw-1.4.0.dist-info/licenses/LICENSE.txt
mafw-1.4.0.dist-info/licenses/NOTICE.txt
mafw-1.4.0.dist-info/RECORD
