Metadata-Version: 2.4
Name: mafw
Version: 1.4.0
Summary: A modular analysis framework
Project-URL: homepage, https://code.europa.eu/kada/mafw/-/blob/main/README.rst
Project-URL: Documentation, https://mafw-e8abfd.pages.code.europa.eu/doc/
Project-URL: Issues, https://code.europa.eu/kada/mafw/-/issues
Project-URL: Source, https://code.europa.eu/kada/mafw
Project-URL: Changelog, https://code.europa.eu/kada/mafw/-/blob/main/CHANGELOG.md
Author-email: BULGHERONI Antonio <Antonio.BULGHERONI@ec.europa.eu>, KRACHLER Michael <Michael.KRACHLER@ec.europa.eu>
License-Expression: EUPL-1.2
License-File: LICENSE.txt
License-File: NOTICE.txt
Classifier: Development Status :: 4 - Beta
Classifier: Environment :: Console
Classifier: Intended Audience :: Science/Research
Classifier: Operating System :: OS Independent
Classifier: Programming Language :: Python
Classifier: Programming Language :: Python :: 3.11
Classifier: Programming Language :: Python :: 3.12
Classifier: Programming Language :: Python :: 3.13
Classifier: Programming Language :: Python :: Implementation :: CPython
Classifier: Topic :: Scientific/Engineering
Requires-Python: >=3.11
Requires-Dist: click>=8.1.8
Requires-Dist: deprecated>=1.2.18
Requires-Dist: peewee>=3.17.9
Requires-Dist: pluggy>=1.5.0
Requires-Dist: rich>=13.9.4
Requires-Dist: tomlkit>=0.13.2
Requires-Dist: typing-extensions>=4.13.0; python_version <= '3.11'
Provides-Extra: all-db
Requires-Dist: psycopg2-binary; extra == 'all-db'
Requires-Dist: psycopg[binary]; extra == 'all-db'
Requires-Dist: pymysql[rsa]; extra == 'all-db'
Provides-Extra: dev
Requires-Dist: auto-changelog; extra == 'dev'
Requires-Dist: matplotlib>=3.10.1; extra == 'dev'
Requires-Dist: pandas[hdf5]>=2.2.3; extra == 'dev'
Requires-Dist: pre-commit; extra == 'dev'
Requires-Dist: psycopg2-binary; extra == 'dev'
Requires-Dist: psycopg[binary]; extra == 'dev'
Requires-Dist: pymysql[rsa]; extra == 'dev'
Requires-Dist: pytest; extra == 'dev'
Requires-Dist: pytest-datadir; extra == 'dev'
Requires-Dist: ruff; extra == 'dev'
Requires-Dist: seaborn>=0.13.2; extra == 'dev'
Requires-Dist: sphinx; extra == 'dev'
Requires-Dist: sphinx-click; extra == 'dev'
Requires-Dist: sphinx-copybutton; extra == 'dev'
Requires-Dist: sphinx-design; extra == 'dev'
Requires-Dist: sphinx-rtd-theme; extra == 'dev'
Requires-Dist: sphinxcontrib-applehelp; extra == 'dev'
Requires-Dist: sphinxcontrib-devhelp; extra == 'dev'
Requires-Dist: sphinxcontrib-external-links; extra == 'dev'
Requires-Dist: sphinxcontrib-htmlhelp; extra == 'dev'
Requires-Dist: sphinxcontrib-jquery; extra == 'dev'
Requires-Dist: sphinxcontrib-jsmath; extra == 'dev'
Requires-Dist: sphinxcontrib-qthelp; extra == 'dev'
Requires-Dist: sphinxcontrib-serializinghtml; extra == 'dev'
Provides-Extra: doc
Requires-Dist: sphinx; extra == 'doc'
Requires-Dist: sphinx-click; extra == 'doc'
Requires-Dist: sphinx-copybutton; extra == 'doc'
Requires-Dist: sphinx-design; extra == 'doc'
Requires-Dist: sphinx-rtd-theme; extra == 'doc'
Requires-Dist: sphinxcontrib-applehelp; extra == 'doc'
Requires-Dist: sphinxcontrib-devhelp; extra == 'doc'
Requires-Dist: sphinxcontrib-external-links; extra == 'doc'
Requires-Dist: sphinxcontrib-htmlhelp; extra == 'doc'
Requires-Dist: sphinxcontrib-jquery; extra == 'doc'
Requires-Dist: sphinxcontrib-jsmath; extra == 'doc'
Requires-Dist: sphinxcontrib-qthelp; extra == 'doc'
Requires-Dist: sphinxcontrib-serializinghtml; extra == 'doc'
Provides-Extra: seaborn
Requires-Dist: matplotlib>=3.10.1; extra == 'seaborn'
Requires-Dist: pandas[hdf5]>=2.2.3; extra == 'seaborn'
Requires-Dist: seaborn>=0.13.2; extra == 'seaborn'
Provides-Extra: test
Requires-Dist: pytest; extra == 'test'
Requires-Dist: pytest-datadir; extra == 'test'
